SakuRose/__init__.py
SakuRose/data_handler.py
SakuRose/other.py
SakuRose/randomizer.py
sakurose-1.8.5.dist-info/LICENSE
sakurose-1.8.5.dist-info/METADATA
sakurose-1.8.5.dist-info/WHEEL
sakurose-1.8.5.dist-info/top_level.txt
sakurose-1.8.5.dist-info/RECORD
