Metadata-Version: 2.1
Name: sakurose
Version: 1.8.5
Summary: SakuRose: Simplifica la creación de códigos en Python3.9 o superior, de uso gratuito e ilimitado.
Author: InsAnya606
Author-email: insanyadev@gmail.com
Classifier: Programming Language :: Python :: 3
Classifier: License :: OSI Approved :: MIT License
Classifier: Operating System :: OS Independent
Requires-Python: >=3.6
License-File: LICENSE
Requires-Dist: Flask
Requires-Dist: Pillow
Requires-Dist: discord.py
Requires-Dist: pytz
Requires-Dist: requests
